bilby_numpyro/__init__.py
bilby_numpyro/numpyro.py
bilby_numpyro/utils.py
tests/test_bilby_integration.py
bilby_numpyro-0.0.1.dist-info/LICENSE
bilby_numpyro-0.0.1.dist-info/METADATA
bilby_numpyro-0.0.1.dist-info/WHEEL
bilby_numpyro-0.0.1.dist-info/entry_points.txt
bilby_numpyro-0.0.1.dist-info/top_level.txt
bilby_numpyro-0.0.1.dist-info/RECORD
