Metadata-Version: 2.1
Name: bilby_numpyro
Version: 0.0.1
Author-email: your name <your@email.com>
License: MIT
Classifier: Programming Language :: Python :: 3
Requires-Python: >=3.10
License-File: LICENSE
Requires-Dist: arviz
Requires-Dist: bilby>2.2.4
Requires-Dist: jax
Requires-Dist: numpy
Requires-Dist: numpyro
Provides-Extra: test
Requires-Dist: pytest; extra == "test"
